pycopy/__init__.py
pycopy/__main__.py
pycopy/fs_sync.py
pycopy/hashing.py
pycopy/logging.py
pycopy/terminal_formatting.py
pycopy/version.py
pycopy-2025.7.54.dist-info/METADATA
pycopy-2025.7.54.dist-info/WHEEL
pycopy-2025.7.54.dist-info/entry_points.txt
pycopy-2025.7.54.dist-info/licenses/LICENSE.txt
pycopy-2025.7.54.dist-info/RECORD
